trident/__init__.py
trident/cli.py
trident/client.py
izihawa_trident_client-1.4.2.dist-info/METADATA
izihawa_trident_client-1.4.2.dist-info/WHEEL
izihawa_trident_client-1.4.2.dist-info/entry_points.txt
izihawa_trident_client-1.4.2.dist-info/RECORD
