Metadata-Version: 2.1
Name: izihawa-trident-client
Version: 1.4.2
Summary: 
Author: Pasha Podolsky
Author-email: ppodolsky@me.com
Requires-Python: >=3.9,<3.14
Classifier: Programming Language :: Python :: 3
Classifier: Programming Language :: Python :: 3.9
Classifier: Programming Language :: Python :: 3.10
Classifier: Programming Language :: Python :: 3.11
Classifier: Programming Language :: Python :: 3.12
Requires-Dist: aiobaseclient (>=0.4.10,<0.5.0)
Requires-Dist: aiofiles (>=23.2.1,<24.0.0)
